usepy_plugin_notify/__init__.py
usepy_plugin_notify/channels/__init__.py
usepy_plugin_notify/channels/bark.py
usepy_plugin_notify/channels/base.py
usepy_plugin_notify/channels/chanify.py
usepy_plugin_notify/channels/ding.py
usepy_plugin_notify/channels/email.py
usepy_plugin_notify/channels/pushdeer.py
usepy_plugin_notify/channels/pushover.py
usepy_plugin_notify/channels/wechat.py
usepy_plugin_notify/notification.py
usepy_plugin_notify-0.3.0.dist-info/METADATA
usepy_plugin_notify-0.3.0.dist-info/WHEEL
usepy_plugin_notify-0.3.0.dist-info/RECORD
