Metadata-Version: 2.1
Name: usepy-plugin-notify
Version: 0.3.0
Summary: 一个简单可扩展的异步消息通知库
Author: miclon
Author-email: jcnd@163.com
Requires-Python: >=3.8,<4.0
Classifier: Programming Language :: Python :: 3
Classifier: Programming Language :: Python :: 3.8
Classifier: Programming Language :: Python :: 3.9
Classifier: Programming Language :: Python :: 3.10
Classifier: Programming Language :: Python :: 3.11
Requires-Dist: httpx (>=0.23.3,<0.24.0)
Requires-Dist: usepy (>=0.2.6,<0.3.0)
